wktplot/__init__.py
wktplot/common/__init__.py
wktplot/common/file_utils.py
wktplot/common/types.py
wktplot/mappers/__init__.py
wktplot/mappers/base.py
wktplot/mappers/osm.py
wktplot/mappers/standard.py
wktplot/plots/__init__.py
wktplot/plots/base.py
wktplot/plots/osm.py
wktplot/plots/standard.py
wktplot-2.3.2.dist-info/LICENSE
wktplot-2.3.2.dist-info/METADATA
wktplot-2.3.2.dist-info/WHEEL
wktplot-2.3.2.dist-info/top_level.txt
wktplot-2.3.2.dist-info/zip-safe
wktplot-2.3.2.dist-info/RECORD
