Metadata-Version: 2.1
Name: wktplot
Version: 2.3.2
Summary: Well-known-text and shapely object visualiation library
Home-page: https://github.com/FuzzFoundation/WKTPlot
Author: Michael Simpson, Gerald Sornsen
Author-email: mikeysimpson4@gmail.com, gerald@sornsen.io
License: MIT
Keywords: well-known-text,shapely,bokeh,geo-spatial,visualization
Platform: any
Classifier: License :: OSI Approved :: MIT License
Classifier: Programming Language :: Python
Classifier: Programming Language :: Python :: 3.7
Classifier: Programming Language :: Python :: 3.8
Classifier: Programming Language :: Python :: 3.9
Classifier: Programming Language :: Python :: 3.10
Classifier: Natural Language :: English
Classifier: Operating System :: OS Independent
Classifier: Development Status :: 5 - Production/Stable
Classifier: Intended Audience :: Developers
Classifier: Topic :: Software Development :: Libraries
Requires-Python: >=3.7
License-File: LICENSE
Requires-Dist: bokeh (==2.4.2)
Requires-Dist: jinja2 (==3.0.3)
Requires-Dist: markupsafe (==2.0.1)
Requires-Dist: numpy (==1.21.5)
Requires-Dist: packaging (==21.3)
Requires-Dist: pillow (==8.4.0)
Requires-Dist: pyparsing (==3.0.6)
Requires-Dist: pyyaml (==6.0)
Requires-Dist: shapely (>=1.8.1)
Requires-Dist: tornado (==6.1)
Requires-Dist: typing-extensions (==4.0.1)
Provides-Extra: test
Requires-Dist: flake8 (>=4.0.1) ; extra == 'test'
Requires-Dist: pytest (>=6.1.2) ; extra == 'test'
Requires-Dist: pytest-cov (>=2.10.1) ; extra == 'test'
Requires-Dist: pytest-mock (>=3.8.2) ; extra == 'test'
